Metadata-Version: 2.1
Name: svgelements
Version: 1.9.5
Summary: Svg Elements Parsing
Home-page: https://github.com/meerk40t/svgelements
Author: Tatarize
Author-email: tatarize@gmail.com
License: MIT
Keywords: svg,path,elements,matrix,vector,parser
Platform: UNKNOWN
Classifier: Development Status :: 5 - Production/Stable
Classifier: Intended Audience :: Developers
Classifier: License :: OSI Approved :: MIT License
Classifier: Operating System :: OS Independent
Classifier: Programming Language :: Python
Classifier: Programming Language :: Python :: 3.6
Classifier: Programming Language :: Python :: 3.7
Classifier: Programming Language :: Python :: 3.8
Classifier: Programming Language :: Python :: 3.9
Classifier: Programming Language :: Python :: 3.10
Classifier: Programming Language :: Python :: 3.11
Classifier: Topic :: Multimedia :: Graphics
Classifier: Topic :: Multimedia :: Graphics :: Editors :: Vector-Based
Classifier: Topic :: Software Development :: Libraries :: Python Modules
Classifier: Topic :: Utilities
